{
  "schema_version": "round32_big_score_tail_optimization_v1",
  "created_at": "2026-06-29T00:35:00+08:00",
  "status": "completed",
  "boundary": {
    "raw_poisson_changed": false,
    "expected_goals_changed": false,
    "probabilities_1x2_changed": false,
    "totals_changed": false,
    "headline_score_changed": false,
    "red_team_or_betting_gate_changed": false
  },
  "thread_participation": {
    "modeler": {
      "thread_id": "019edb8f-536a-7100-84da-e13bfecb0def",
      "output": "data/thread_outputs/round32-big-score-tail-optimization-20260629/modeler-tail-review.json",
      "status": "completed"
    },
    "tactics": {
      "thread_id": "019edb8f-1c20-7f52-a33d-fde56a56d4a7",
      "output": "data/thread_outputs/round32-big-score-tail-optimization-20260629/tactics-tail-factors.json",
      "status": "completed_or_main_reconstructed_md_from_json"
    },
    "red_team": {
      "thread_id": "019edb8f-9069-7ca2-843a-4ec0f34a1b74",
      "output": "data/thread_outputs/round32-big-score-tail-optimization-20260629/red-team-tail-review-clean.json",
      "status": "completed_cleaned_from_json_due_markdown_encoding",
      "verdict": "revise"
    }
  },
  "visibility_summary": {
    "high": [
      "M74",
      "M76",
      "M77",
      "M80",
      "M82",
      "M84"
    ],
    "medium": [
      "M78",
      "M81"
    ],
    "low": [
      "M73",
      "M75",
      "M79",
      "M83"
    ],
    "not_triggered_or_json_only": [
      "M73"
    ]
  },
  "matches": [
    {
      "match_id": "M73",
      "match": "南非 vs 加拿大",
      "favorite": "加拿大",
      "expected_goals": {
        "team_a": 1.08,
        "team_b": 1.34,
        "total": 2.42,
        "xg_gap": 0.26
      },
      "probabilities_1x2": {
        "team_a_win": 0.3012,
        "draw": 0.2724,
        "team_b_win": 0.4265,
        "sum": 1
      },
      "totals_probabilities": {
        "over_2_5": 0.4355,
        "under_2_5": 0.5645,
        "btts_yes": 0.4875,
        "btts_no": 0.5125
      },
      "knockout_big_score_tail_layer": {
        "trigger_status": "not_triggered",
        "tail_visibility_level": "low",
        "modeler_tail_visibility_level": "low",
        "tactical_tail_classification": "limited_tail_do_not_amplify",
        "red_team_verdict": "revise",
        "red_team_mainline_forbidden": true,
        "reason": "总 xG 2.42、Over2.5 43.6%、矩阵 tail 0.35%，淘汰赛谨慎和南非低位韧性更支持窄比分。",
        "recommended_display": "不新增显性大比分尾部，只在质量备注中保留加拿大 1-3/0-3 等低概率追分尾部。",
        "amplifiers_to_check": [
          "early_goal_before_30m",
          "red_card_or_second_yellow",
          "set_piece_goal_or_penalty",
          "goalkeeper_error_or_save_swing",
          "late_game_trailing_team_chase",
          "extra_time_not_in_90m_model"
        ],
        "red_team_guardrails": [
          "只作为 tail_visibility / risk layer 接入，不直接改 1X2、xG、大小球或 headline score。",
          "T-75 官方首发、最终伤停/分钟限制和同源赔率未闭合前，不能把大比分尾部写成可执行结论。",
          "红牌、早球、点球、门将失误和晚段追分只能作为条件尾部，不得作为稳定主预测。",
          "必须保留 raw Poisson 和 adjusted headline score，防止从过保守反向过度补偿。",
          "防止与 totals、BTTS、player_state、tactical_volatility 重复计权。"
        ],
        "no_probability_change": true,
        "no_headline_score_change": true,
        "no_betting_gate_change": true,
        "applied_at": "2026-06-29T00:35:00+08:00"
      },
      "big_score_tail_paths": {
        "strong_team_breakthrough_path": {
          "probability": 0.1388,
          "top_scores": [
            {
              "score": "1-3",
              "probability": 0.0385
            },
            {
              "score": "0-3",
              "probability": 0.0357
            },
            {
              "score": "2-3",
              "probability": 0.0208
            },
            {
              "score": "1-4",
              "probability": 0.0129
            },
            {
              "score": "0-4",
              "probability": 0.0119
            },
            {
              "score": "2-4",
              "probability": 0.007
            }
          ]
        },
        "open_shootout_path": {
          "probability": 0.2009,
          "top_scores": [
            {
              "score": "2-2",
              "probability": 0.0466
            },
            {
              "score": "1-3",
              "probability": 0.0385
            },
            {
              "score": "3-1",
              "probability": 0.025
            },
            {
              "score": "2-3",
              "probability": 0.0208
            },
            {
              "score": "3-2",
              "probability": 0.0168
            },
            {
              "score": "1-4",
              "probability": 0.0129
            }
          ]
        },
        "weak_team_collapse_path": {
          "probability": 0.0691,
          "top_scores": [
            {
              "score": "0-3",
              "probability": 0.0357
            },
            {
              "score": "1-4",
              "probability": 0.0129
            },
            {
              "score": "0-4",
              "probability": 0.0119
            },
            {
              "score": "1-5",
              "probability": 0.0035
            },
            {
              "score": "0-5",
              "probability": 0.0032
            },
            {
              "score": "2-5",
              "probability": 0.0019
            }
          ]
        },
        "late_game_chase_tail": {
          "probability": 0.1733,
          "top_scores": [
            {
              "score": "2-2",
              "probability": 0.0466
            },
            {
              "score": "1-3",
              "probability": 0.0385
            },
            {
              "score": "3-1",
              "probability": 0.025
            },
            {
              "score": "2-3",
              "probability": 0.0208
            },
            {
              "score": "3-2",
              "probability": 0.0168
            },
            {
              "score": "3-3",
              "probability": 0.0075
            }
          ]
        },
        "unallocated_above_5x5_tail": 0.0035
      },
      "margin_bands": {
        "favorite_by_1": 0.2289,
        "favorite_by_2": 0.126,
        "favorite_by_3plus": 0.0691,
        "draw": 0.2724,
        "underdog_by_1": 0.1844,
        "underdog_by_2plus": 0.1159,
        "total_goals_4plus_in_matrix": 0.2221,
        "both_teams_2plus_in_matrix": 0.1127
      },
      "late_game_tail_note": "若一方60分钟后落后、早球、红牌/二黄、点球/定位球、门将失误或连续进攻换人出现，本场上沿比分尾部会被放大；赛前只作条件路径展示。",
      "tactical_tail_classification": "limited_tail_do_not_amplify",
      "tactical_triggers": [
        "Canada transition_attack +0.45",
        "South Africa low block and set_piece +0.25",
        "Canada transition_defense_risk -0.35"
      ],
      "markdown_path": "比赛/未开始比赛/32强/M73_2026-06-28_南非_vs_加拿大_量化预测_v3.md",
      "markdown_status": "updated"
    },
    {
      "match_id": "M74",
      "match": "德国 vs 巴拉圭",
      "favorite": "德国",
      "expected_goals": {
        "team_a": 2.1,
        "team_b": 0.78,
        "total": 2.88,
        "xg_gap": 1.32
      },
      "probabilities_1x2": {
        "team_a_win": 0.6793,
        "draw": 0.1933,
        "team_b_win": 0.1274,
        "sum": 1
      },
      "totals_probabilities": {
        "over_2_5": 0.5494,
        "under_2_5": 0.4506,
        "btts_yes": 0.4753,
        "btts_no": 0.5247
      },
      "knockout_big_score_tail_layer": {
        "trigger_status": "triggered",
        "tail_visibility_level": "high",
        "modeler_tail_visibility_level": "high",
        "tactical_tail_classification": "favorite_runaway_explicit",
        "red_team_verdict": "revise",
        "red_team_mainline_forbidden": false,
        "reason": "德国 1X2 67.9%、xG 2.10-0.78、强度差 18，具备早球后控场扩大和巴拉圭追分暴露路径。",
        "recommended_display": "新增强队打穿与弱队崩盘尾部：3-0、3-1、4-0、4-1；headline 仍用 adjusted/ranked score，不把大比分强行设为首选。",
        "amplifiers_to_check": [
          "early_goal_before_30m",
          "red_card_or_second_yellow",
          "set_piece_goal_or_penalty",
          "goalkeeper_error_or_save_swing",
          "late_game_trailing_team_chase",
          "extra_time_not_in_90m_model"
        ],
        "red_team_guardrails": [
          "只作为 tail_visibility / risk layer 接入，不直接改 1X2、xG、大小球或 headline score。",
          "T-75 官方首发、最终伤停/分钟限制和同源赔率未闭合前，不能把大比分尾部写成可执行结论。",
          "红牌、早球、点球、门将失误和晚段追分只能作为条件尾部，不得作为稳定主预测。",
          "必须保留 raw Poisson 和 adjusted headline score，防止从过保守反向过度补偿。",
          "防止与 totals、BTTS、player_state、tactical_volatility 重复计权。"
        ],
        "no_probability_change": true,
        "no_headline_score_change": true,
        "no_betting_gate_change": true,
        "applied_at": "2026-06-29T00:35:00+08:00"
      },
      "big_score_tail_paths": {
        "strong_team_breakthrough_path": {
          "probability": 0.3206,
          "top_scores": [
            {
              "score": "3-0",
              "probability": 0.0866
            },
            {
              "score": "3-1",
              "probability": 0.0676
            },
            {
              "score": "4-0",
              "probability": 0.0455
            },
            {
              "score": "4-1",
              "probability": 0.0355
            },
            {
              "score": "3-2",
              "probability": 0.0264
            },
            {
              "score": "5-0",
              "probability": 0.0191
            }
          ]
        },
        "open_shootout_path": {
          "probability": 0.2397,
          "top_scores": [
            {
              "score": "3-1",
              "probability": 0.0676
            },
            {
              "score": "2-2",
              "probability": 0.0377
            },
            {
              "score": "4-1",
              "probability": 0.0355
            },
            {
              "score": "3-2",
              "probability": 0.0264
            },
            {
              "score": "5-1",
              "probability": 0.0149
            },
            {
              "score": "4-2",
              "probability": 0.0138
            }
          ]
        },
        "weak_team_collapse_path": {
          "probability": 0.2074,
          "top_scores": [
            {
              "score": "3-0",
              "probability": 0.0866
            },
            {
              "score": "4-0",
              "probability": 0.0455
            },
            {
              "score": "4-1",
              "probability": 0.0355
            },
            {
              "score": "5-0",
              "probability": 0.0191
            },
            {
              "score": "5-1",
              "probability": 0.0149
            },
            {
              "score": "5-2",
              "probability": 0.0058
            }
          ]
        },
        "late_game_chase_tail": {
          "probability": 0.1811,
          "top_scores": [
            {
              "score": "3-1",
              "probability": 0.0676
            },
            {
              "score": "2-2",
              "probability": 0.0377
            },
            {
              "score": "3-2",
              "probability": 0.0264
            },
            {
              "score": "4-2",
              "probability": 0.0138
            },
            {
              "score": "2-3",
              "probability": 0.0098
            },
            {
              "score": "1-3",
              "probability": 0.0093
            }
          ]
        },
        "unallocated_above_5x5_tail": 0.0206
      },
      "margin_bands": {
        "favorite_by_1": 0.2447,
        "favorite_by_2": 0.2067,
        "favorite_by_3plus": 0.2074,
        "draw": 0.1933,
        "underdog_by_1": 0.0909,
        "underdog_by_2plus": 0.0363,
        "total_goals_4plus_in_matrix": 0.3053,
        "both_teams_2plus_in_matrix": 0.1103
      },
      "late_game_tail_note": "若一方60分钟后落后、早球、红牌/二黄、点球/定位球、门将失误或连续进攻换人出现，本场上沿比分尾部会被放大；赛前只作条件路径展示。",
      "tactical_tail_classification": "favorite_runaway_explicit",
      "tactical_triggers": [
        "Germany pressing +0.40",
        "Germany central_control +0.55",
        "Paraguay central_control -0.45",
        "Paraguay transition_defense -0.35"
      ],
      "markdown_path": "比赛/未开始比赛/32强/M74_2026-06-29_德国_vs_巴拉圭_量化预测_v3.md",
      "markdown_status": "updated"
    },
    {
      "match_id": "M75",
      "match": "荷兰 vs 摩洛哥",
      "favorite": "荷兰",
      "expected_goals": {
        "team_a": 1.48,
        "team_b": 1.12,
        "total": 2.6,
        "xg_gap": 0.36
      },
      "probabilities_1x2": {
        "team_a_win": 0.4545,
        "draw": 0.2588,
        "team_b_win": 0.2867,
        "sum": 1
      },
      "totals_probabilities": {
        "over_2_5": 0.4816,
        "under_2_5": 0.5184,
        "btts_yes": 0.5204,
        "btts_no": 0.4796
      },
      "knockout_big_score_tail_layer": {
        "trigger_status": "observe",
        "tail_visibility_level": "low",
        "modeler_tail_visibility_level": "medium_low",
        "tactical_tail_classification": "open_two_way_tail",
        "red_team_verdict": "revise",
        "red_team_mainline_forbidden": true,
        "reason": "荷兰有小优势但 xG 1.48-1.12 不足以支持强队打穿，更多是相近实力下的早球/转换尾部。",
        "recommended_display": "只新增观察级开放尾部：3-1、2-2、3-2；不作为主展示。",
        "amplifiers_to_check": [
          "early_goal_before_30m",
          "red_card_or_second_yellow",
          "set_piece_goal_or_penalty",
          "goalkeeper_error_or_save_swing",
          "late_game_trailing_team_chase",
          "extra_time_not_in_90m_model"
        ],
        "red_team_guardrails": [
          "只作为 tail_visibility / risk layer 接入，不直接改 1X2、xG、大小球或 headline score。",
          "T-75 官方首发、最终伤停/分钟限制和同源赔率未闭合前，不能把大比分尾部写成可执行结论。",
          "红牌、早球、点球、门将失误和晚段追分只能作为条件尾部，不得作为稳定主预测。",
          "必须保留 raw Poisson 和 adjusted headline score，防止从过保守反向过度补偿。",
          "防止与 totals、BTTS、player_state、tactical_volatility 重复计权。"
        ],
        "no_probability_change": true,
        "no_headline_score_change": true,
        "no_betting_gate_change": true,
        "applied_at": "2026-06-29T00:35:00+08:00"
      },
      "big_score_tail_paths": {
        "strong_team_breakthrough_path": {
          "probability": 0.1678,
          "top_scores": [
            {
              "score": "3-1",
              "probability": 0.0449
            },
            {
              "score": "3-0",
              "probability": 0.0401
            },
            {
              "score": "3-2",
              "probability": 0.0252
            },
            {
              "score": "4-1",
              "probability": 0.0166
            },
            {
              "score": "4-0",
              "probability": 0.0148
            },
            {
              "score": "4-2",
              "probability": 0.0093
            }
          ]
        },
        "open_shootout_path": {
          "probability": 0.2334,
          "top_scores": [
            {
              "score": "2-2",
              "probability": 0.051
            },
            {
              "score": "3-1",
              "probability": 0.0449
            },
            {
              "score": "1-3",
              "probability": 0.0257
            },
            {
              "score": "3-2",
              "probability": 0.0252
            },
            {
              "score": "2-3",
              "probability": 0.019
            },
            {
              "score": "4-1",
              "probability": 0.0166
            }
          ]
        },
        "weak_team_collapse_path": {
          "probability": 0.0836,
          "top_scores": [
            {
              "score": "3-0",
              "probability": 0.0401
            },
            {
              "score": "4-1",
              "probability": 0.0166
            },
            {
              "score": "4-0",
              "probability": 0.0148
            },
            {
              "score": "5-1",
              "probability": 0.0049
            },
            {
              "score": "5-0",
              "probability": 0.0044
            },
            {
              "score": "5-2",
              "probability": 0.0028
            }
          ]
        },
        "late_game_chase_tail": {
          "probability": 0.1991,
          "top_scores": [
            {
              "score": "2-2",
              "probability": 0.051
            },
            {
              "score": "3-1",
              "probability": 0.0449
            },
            {
              "score": "1-3",
              "probability": 0.0257
            },
            {
              "score": "3-2",
              "probability": 0.0252
            },
            {
              "score": "2-3",
              "probability": 0.019
            },
            {
              "score": "3-3",
              "probability": 0.0094
            }
          ]
        },
        "unallocated_above_5x5_tail": 0.0052
      },
      "margin_bands": {
        "favorite_by_1": 0.23,
        "favorite_by_2": 0.1365,
        "favorite_by_3plus": 0.0836,
        "draw": 0.2588,
        "underdog_by_1": 0.1739,
        "underdog_by_2plus": 0.1116,
        "total_goals_4plus_in_matrix": 0.2586,
        "both_teams_2plus_in_matrix": 0.1325
      },
      "late_game_tail_note": "若一方60分钟后落后、早球、红牌/二黄、点球/定位球、门将失误或连续进攻换人出现，本场上沿比分尾部会被放大；赛前只作条件路径展示。",
      "tactical_tail_classification": "open_two_way_tail",
      "tactical_triggers": [
        "Netherlands transition_attack +0.35",
        "Morocco transition_attack +0.40",
        "Netherlands transition_defense -0.30",
        "Morocco third-round 4-2 openness noted in Markdown"
      ],
      "markdown_path": "比赛/未开始比赛/32强/M75_2026-06-29_荷兰_vs_摩洛哥_量化预测_v3.md",
      "markdown_status": "updated"
    },
    {
      "match_id": "M76",
      "match": "巴西 vs 日本",
      "favorite": "巴西",
      "expected_goals": {
        "team_a": 1.92,
        "team_b": 1.08,
        "total": 3,
        "xg_gap": 0.84
      },
      "probabilities_1x2": {
        "team_a_win": 0.5694,
        "draw": 0.2206,
        "team_b_win": 0.21,
        "sum": 1
      },
      "totals_probabilities": {
        "over_2_5": 0.5768,
        "under_2_5": 0.4232,
        "btts_yes": 0.5636,
        "btts_no": 0.4364
      },
      "knockout_big_score_tail_layer": {
        "trigger_status": "triggered",
        "tail_visibility_level": "high",
        "modeler_tail_visibility_level": "medium_high",
        "tactical_tail_classification": "favorite_runaway_with_two_way_counter",
        "red_team_verdict": "revise",
        "red_team_mainline_forbidden": false,
        "reason": "巴西胜率 56.9%、xG 1.92-1.08、Over2.5 57.7%、BTTS 56.4%，raw 1-1 已被 rerank 为 2-1，仍需要显性显示 3球以上上沿。",
        "recommended_display": "新增巴西边路打穿尾部：3-1、3-0、4-1、4-0，并保留日本反击导致 3-2/2-2 的开放尾部。",
        "amplifiers_to_check": [
          "early_goal_before_30m",
          "red_card_or_second_yellow",
          "set_piece_goal_or_penalty",
          "goalkeeper_error_or_save_swing",
          "late_game_trailing_team_chase",
          "extra_time_not_in_90m_model"
        ],
        "red_team_guardrails": [
          "只作为 tail_visibility / risk layer 接入，不直接改 1X2、xG、大小球或 headline score。",
          "T-75 官方首发、最终伤停/分钟限制和同源赔率未闭合前，不能把大比分尾部写成可执行结论。",
          "红牌、早球、点球、门将失误和晚段追分只能作为条件尾部，不得作为稳定主预测。",
          "必须保留 raw Poisson 和 adjusted headline score，防止从过保守反向过度补偿。",
          "防止与 totals、BTTS、player_state、tactical_volatility 重复计权。"
        ],
        "no_probability_change": true,
        "no_headline_score_change": true,
        "no_betting_gate_change": true,
        "applied_at": "2026-06-29T00:35:00+08:00"
      },
      "big_score_tail_paths": {
        "strong_team_breakthrough_path": {
          "probability": 0.269,
          "top_scores": [
            {
              "score": "3-1",
              "probability": 0.0634
            },
            {
              "score": "3-0",
              "probability": 0.0587
            },
            {
              "score": "3-2",
              "probability": 0.0343
            },
            {
              "score": "4-1",
              "probability": 0.0304
            },
            {
              "score": "4-0",
              "probability": 0.0282
            },
            {
              "score": "4-2",
              "probability": 0.0164
            }
          ]
        },
        "open_shootout_path": {
          "probability": 0.2954,
          "top_scores": [
            {
              "score": "3-1",
              "probability": 0.0634
            },
            {
              "score": "2-2",
              "probability": 0.0535
            },
            {
              "score": "3-2",
              "probability": 0.0343
            },
            {
              "score": "4-1",
              "probability": 0.0304
            },
            {
              "score": "1-3",
              "probability": 0.0201
            },
            {
              "score": "2-3",
              "probability": 0.0193
            }
          ]
        },
        "weak_team_collapse_path": {
          "probability": 0.1461,
          "top_scores": [
            {
              "score": "3-0",
              "probability": 0.0587
            },
            {
              "score": "4-1",
              "probability": 0.0304
            },
            {
              "score": "4-0",
              "probability": 0.0282
            },
            {
              "score": "5-1",
              "probability": 0.0117
            },
            {
              "score": "5-0",
              "probability": 0.0108
            },
            {
              "score": "5-2",
              "probability": 0.0063
            }
          ]
        },
        "late_game_chase_tail": {
          "probability": 0.2393,
          "top_scores": [
            {
              "score": "3-1",
              "probability": 0.0634
            },
            {
              "score": "2-2",
              "probability": 0.0535
            },
            {
              "score": "3-2",
              "probability": 0.0343
            },
            {
              "score": "1-3",
              "probability": 0.0201
            },
            {
              "score": "2-3",
              "probability": 0.0193
            },
            {
              "score": "4-2",
              "probability": 0.0164
            }
          ]
        },
        "unallocated_above_5x5_tail": 0.0147
      },
      "margin_bands": {
        "favorite_by_1": 0.2355,
        "favorite_by_2": 0.1739,
        "favorite_by_3plus": 0.1461,
        "draw": 0.2206,
        "underdog_by_1": 0.1324,
        "underdog_by_2plus": 0.0766,
        "total_goals_4plus_in_matrix": 0.3378,
        "both_teams_2plus_in_matrix": 0.1632
      },
      "late_game_tail_note": "若一方60分钟后落后、早球、红牌/二黄、点球/定位球、门将失误或连续进攻换人出现，本场上沿比分尾部会被放大；赛前只作条件路径展示。",
      "tactical_tail_classification": "favorite_runaway_with_two_way_counter",
      "tactical_triggers": [
        "Brazil transition_attack +0.50",
        "Brazil wide_channel +0.45",
        "Japan wide_channel -0.35",
        "Japan set_piece -0.30"
      ],
      "markdown_path": "比赛/未开始比赛/32强/M76_2026-06-29_巴西_vs_日本_量化预测_v3.md",
      "markdown_status": "updated"
    },
    {
      "match_id": "M77",
      "match": "法国 vs 瑞典",
      "favorite": "法国",
      "expected_goals": {
        "team_a": 2.1,
        "team_b": 1.03,
        "total": 3.13,
        "xg_gap": 1.07
      },
      "probabilities_1x2": {
        "team_a_win": 0.6194,
        "draw": 0.2035,
        "team_b_win": 0.1771,
        "sum": 1
      },
      "totals_probabilities": {
        "over_2_5": 0.6053,
        "under_2_5": 0.3947,
        "btts_yes": 0.5643,
        "btts_no": 0.4357
      },
      "knockout_big_score_tail_layer": {
        "trigger_status": "triggered",
        "tail_visibility_level": "high",
        "modeler_tail_visibility_level": "high",
        "tactical_tail_classification": "favorite_runaway_explicit",
        "red_team_verdict": "revise",
        "red_team_mainline_forbidden": false,
        "reason": "法国胜率 61.9%、xG 2.10-1.03、Over2.5 60.5%、BTTS 56.4%，既有强队上限也有对手进球后的开放尾部。",
        "recommended_display": "新增法国强队打穿尾部：3-1、3-0、4-1、4-0；瑞典进球路径存在时优先 3-1/4-1。",
        "amplifiers_to_check": [
          "early_goal_before_30m",
          "red_card_or_second_yellow",
          "set_piece_goal_or_penalty",
          "goalkeeper_error_or_save_swing",
          "late_game_trailing_team_chase",
          "extra_time_not_in_90m_model"
        ],
        "red_team_guardrails": [
          "只作为 tail_visibility / risk layer 接入，不直接改 1X2、xG、大小球或 headline score。",
          "T-75 官方首发、最终伤停/分钟限制和同源赔率未闭合前，不能把大比分尾部写成可执行结论。",
          "红牌、早球、点球、门将失误和晚段追分只能作为条件尾部，不得作为稳定主预测。",
          "必须保留 raw Poisson 和 adjusted headline score，防止从过保守反向过度补偿。",
          "防止与 totals、BTTS、player_state、tactical_volatility 重复计权。"
        ],
        "no_probability_change": true,
        "no_headline_score_change": true,
        "no_betting_gate_change": true,
        "applied_at": "2026-06-29T00:35:00+08:00"
      },
      "big_score_tail_paths": {
        "strong_team_breakthrough_path": {
          "probability": 0.3115,
          "top_scores": [
            {
              "score": "3-1",
              "probability": 0.0695
            },
            {
              "score": "3-0",
              "probability": 0.0675
            },
            {
              "score": "4-1",
              "probability": 0.0365
            },
            {
              "score": "3-2",
              "probability": 0.0358
            },
            {
              "score": "4-0",
              "probability": 0.0354
            },
            {
              "score": "4-2",
              "probability": 0.0188
            }
          ]
        },
        "open_shootout_path": {
          "probability": 0.308,
          "top_scores": [
            {
              "score": "3-1",
              "probability": 0.0695
            },
            {
              "score": "2-2",
              "probability": 0.0511
            },
            {
              "score": "4-1",
              "probability": 0.0365
            },
            {
              "score": "3-2",
              "probability": 0.0358
            },
            {
              "score": "4-2",
              "probability": 0.0188
            },
            {
              "score": "2-3",
              "probability": 0.0176
            }
          ]
        },
        "weak_team_collapse_path": {
          "probability": 0.1775,
          "top_scores": [
            {
              "score": "3-0",
              "probability": 0.0675
            },
            {
              "score": "4-1",
              "probability": 0.0365
            },
            {
              "score": "4-0",
              "probability": 0.0354
            },
            {
              "score": "5-1",
              "probability": 0.0153
            },
            {
              "score": "5-0",
              "probability": 0.0149
            },
            {
              "score": "5-2",
              "probability": 0.0079
            }
          ]
        },
        "late_game_chase_tail": {
          "probability": 0.2422,
          "top_scores": [
            {
              "score": "3-1",
              "probability": 0.0695
            },
            {
              "score": "2-2",
              "probability": 0.0511
            },
            {
              "score": "3-2",
              "probability": 0.0358
            },
            {
              "score": "4-2",
              "probability": 0.0188
            },
            {
              "score": "2-3",
              "probability": 0.0176
            },
            {
              "score": "1-3",
              "probability": 0.0167
            }
          ]
        },
        "unallocated_above_5x5_tail": 0.0211
      },
      "margin_bands": {
        "favorite_by_1": 0.2341,
        "favorite_by_2": 0.1874,
        "favorite_by_3plus": 0.1775,
        "draw": 0.2035,
        "underdog_by_1": 0.1148,
        "underdog_by_2plus": 0.0617,
        "total_goals_4plus_in_matrix": 0.3608,
        "both_teams_2plus_in_matrix": 0.1648
      },
      "late_game_tail_note": "若一方60分钟后落后、早球、红牌/二黄、点球/定位球、门将失误或连续进攻换人出现，本场上沿比分尾部会被放大；赛前只作条件路径展示。",
      "tactical_tail_classification": "favorite_runaway_explicit",
      "tactical_triggers": [
        "France transition_attack +0.50",
        "France wide_channel +0.35",
        "Sweden transition_defense -0.35",
        "Sweden defensive_line_risk -0.35"
      ],
      "markdown_path": "比赛/未开始比赛/32强/M77_2026-06-30_法国_vs_瑞典_量化预测_v3.md",
      "markdown_status": "updated"
    },
    {
      "match_id": "M78",
      "match": "科特迪瓦 vs 挪威",
      "favorite": "挪威",
      "expected_goals": {
        "team_a": 1.39,
        "team_b": 1.62,
        "total": 3.01,
        "xg_gap": 0.23
      },
      "probabilities_1x2": {
        "team_a_win": 0.3292,
        "draw": 0.2408,
        "team_b_win": 0.43,
        "sum": 1
      },
      "totals_probabilities": {
        "over_2_5": 0.579,
        "under_2_5": 0.421,
        "btts_yes": 0.6023,
        "btts_no": 0.3977
      },
      "knockout_big_score_tail_layer": {
        "trigger_status": "triggered",
        "tail_visibility_level": "medium",
        "modeler_tail_visibility_level": "medium_high",
        "tactical_tail_classification": "open_two_way_tail",
        "red_team_verdict": "revise",
        "red_team_mainline_forbidden": true,
        "reason": "总 xG 3.01、Over2.5 57.9%、BTTS 60.2%，科特迪瓦/挪威是典型 close-strength open-game tail。",
        "recommended_display": "新增开放对攻尾部：2-2、2-3、3-2、1-3、3-3；重点不是强队碾压，而是互相拉开后的总进球尾部。",
        "amplifiers_to_check": [
          "early_goal_before_30m",
          "red_card_or_second_yellow",
          "set_piece_goal_or_penalty",
          "goalkeeper_error_or_save_swing",
          "late_game_trailing_team_chase",
          "extra_time_not_in_90m_model"
        ],
        "red_team_guardrails": [
          "只作为 tail_visibility / risk layer 接入，不直接改 1X2、xG、大小球或 headline score。",
          "T-75 官方首发、最终伤停/分钟限制和同源赔率未闭合前，不能把大比分尾部写成可执行结论。",
          "红牌、早球、点球、门将失误和晚段追分只能作为条件尾部，不得作为稳定主预测。",
          "必须保留 raw Poisson 和 adjusted headline score，防止从过保守反向过度补偿。",
          "防止与 totals、BTTS、player_state、tactical_volatility 重复计权。"
        ],
        "no_probability_change": true,
        "no_headline_score_change": true,
        "no_betting_gate_change": true,
        "applied_at": "2026-06-29T00:35:00+08:00"
      },
      "big_score_tail_paths": {
        "strong_team_breakthrough_path": {
          "probability": 0.1891,
          "top_scores": [
            {
              "score": "1-3",
              "probability": 0.0485
            },
            {
              "score": "0-3",
              "probability": 0.0349
            },
            {
              "score": "2-3",
              "probability": 0.0337
            },
            {
              "score": "1-4",
              "probability": 0.0197
            },
            {
              "score": "0-4",
              "probability": 0.0141
            },
            {
              "score": "2-4",
              "probability": 0.0137
            }
          ]
        },
        "open_shootout_path": {
          "probability": 0.317,
          "top_scores": [
            {
              "score": "2-2",
              "probability": 0.0625
            },
            {
              "score": "1-3",
              "probability": 0.0485
            },
            {
              "score": "3-1",
              "probability": 0.0357
            },
            {
              "score": "2-3",
              "probability": 0.0337
            },
            {
              "score": "3-2",
              "probability": 0.029
            },
            {
              "score": "1-4",
              "probability": 0.0197
            }
          ]
        },
        "weak_team_collapse_path": {
          "probability": 0.0841,
          "top_scores": [
            {
              "score": "0-3",
              "probability": 0.0349
            },
            {
              "score": "1-4",
              "probability": 0.0197
            },
            {
              "score": "0-4",
              "probability": 0.0141
            },
            {
              "score": "1-5",
              "probability": 0.0064
            },
            {
              "score": "0-5",
              "probability": 0.0046
            },
            {
              "score": "2-5",
              "probability": 0.0044
            }
          ]
        },
        "late_game_chase_tail": {
          "probability": 0.2678,
          "top_scores": [
            {
              "score": "2-2",
              "probability": 0.0625
            },
            {
              "score": "1-3",
              "probability": 0.0485
            },
            {
              "score": "3-1",
              "probability": 0.0357
            },
            {
              "score": "2-3",
              "probability": 0.0337
            },
            {
              "score": "3-2",
              "probability": 0.029
            },
            {
              "score": "3-3",
              "probability": 0.0156
            }
          ]
        },
        "unallocated_above_5x5_tail": 0.0095
      },
      "margin_bands": {
        "favorite_by_1": 0.2105,
        "favorite_by_2": 0.129,
        "favorite_by_3plus": 0.0841,
        "draw": 0.2408,
        "underdog_by_1": 0.1806,
        "underdog_by_2plus": 0.1455,
        "total_goals_4plus_in_matrix": 0.3455,
        "both_teams_2plus_in_matrix": 0.1908
      },
      "late_game_tail_note": "若一方60分钟后落后、早球、红牌/二黄、点球/定位球、门将失误或连续进攻换人出现，本场上沿比分尾部会被放大；赛前只作条件路径展示。",
      "tactical_tail_classification": "open_two_way_tail",
      "tactical_triggers": [
        "Ivory Coast transition_attack +0.35",
        "Norway transition_attack +0.40",
        "Norway transition_defense -0.35",
        "Norway defensive_line_risk -0.35"
      ],
      "markdown_path": "比赛/未开始比赛/32强/M78_2026-06-30_科特迪瓦_vs_挪威_量化预测_v3.md",
      "markdown_status": "updated"
    },
    {
      "match_id": "M79",
      "match": "墨西哥 vs 厄瓜多尔",
      "favorite": "墨西哥",
      "expected_goals": {
        "team_a": 1.44,
        "team_b": 1.24,
        "total": 2.68,
        "xg_gap": 0.2
      },
      "probabilities_1x2": {
        "team_a_win": 0.4173,
        "draw": 0.2578,
        "team_b_win": 0.3249,
        "sum": 1
      },
      "totals_probabilities": {
        "over_2_5": 0.5015,
        "under_2_5": 0.4985,
        "btts_yes": 0.5423,
        "btts_no": 0.4577
      },
      "knockout_big_score_tail_layer": {
        "trigger_status": "observe",
        "tail_visibility_level": "low",
        "modeler_tail_visibility_level": "medium_low",
        "tactical_tail_classification": "do_not_amplify",
        "red_team_verdict": "revise",
        "red_team_mainline_forbidden": true,
        "reason": "墨西哥/厄瓜多尔接近均衡，总 xG 2.68、Over2.5 50.2%，尾部主要来自早球和定位球波动。",
        "recommended_display": "只新增观察级 2-2/3-1/1-3 尾部，不应把大比分写进主路径。",
        "amplifiers_to_check": [
          "early_goal_before_30m",
          "red_card_or_second_yellow",
          "set_piece_goal_or_penalty",
          "goalkeeper_error_or_save_swing",
          "late_game_trailing_team_chase",
          "extra_time_not_in_90m_model"
        ],
        "red_team_guardrails": [
          "只作为 tail_visibility / risk layer 接入，不直接改 1X2、xG、大小球或 headline score。",
          "T-75 官方首发、最终伤停/分钟限制和同源赔率未闭合前，不能把大比分尾部写成可执行结论。",
          "红牌、早球、点球、门将失误和晚段追分只能作为条件尾部，不得作为稳定主预测。",
          "必须保留 raw Poisson 和 adjusted headline score，防止从过保守反向过度补偿。",
          "防止与 totals、BTTS、player_state、tactical_volatility 重复计权。"
        ],
        "no_probability_change": true,
        "no_headline_score_change": true,
        "no_betting_gate_change": true,
        "applied_at": "2026-06-29T00:35:00+08:00"
      },
      "big_score_tail_paths": {
        "strong_team_breakthrough_path": {
          "probability": 0.1554,
          "top_scores": [
            {
              "score": "3-1",
              "probability": 0.0423
            },
            {
              "score": "3-0",
              "probability": 0.0341
            },
            {
              "score": "3-2",
              "probability": 0.0262
            },
            {
              "score": "4-1",
              "probability": 0.0152
            },
            {
              "score": "4-0",
              "probability": 0.0123
            },
            {
              "score": "4-2",
              "probability": 0.0094
            }
          ]
        },
        "open_shootout_path": {
          "probability": 0.2516,
          "top_scores": [
            {
              "score": "2-2",
              "probability": 0.0547
            },
            {
              "score": "3-1",
              "probability": 0.0423
            },
            {
              "score": "1-3",
              "probability": 0.0314
            },
            {
              "score": "3-2",
              "probability": 0.0262
            },
            {
              "score": "2-3",
              "probability": 0.0226
            },
            {
              "score": "4-1",
              "probability": 0.0152
            }
          ]
        },
        "weak_team_collapse_path": {
          "probability": 0.0722,
          "top_scores": [
            {
              "score": "3-0",
              "probability": 0.0341
            },
            {
              "score": "4-1",
              "probability": 0.0152
            },
            {
              "score": "4-0",
              "probability": 0.0123
            },
            {
              "score": "5-1",
              "probability": 0.0044
            },
            {
              "score": "5-0",
              "probability": 0.0035
            },
            {
              "score": "5-2",
              "probability": 0.0027
            }
          ]
        },
        "late_game_chase_tail": {
          "probability": 0.2155,
          "top_scores": [
            {
              "score": "2-2",
              "probability": 0.0547
            },
            {
              "score": "3-1",
              "probability": 0.0423
            },
            {
              "score": "1-3",
              "probability": 0.0314
            },
            {
              "score": "3-2",
              "probability": 0.0262
            },
            {
              "score": "2-3",
              "probability": 0.0226
            },
            {
              "score": "3-3",
              "probability": 0.0108
            }
          ]
        },
        "unallocated_above_5x5_tail": 0.0054
      },
      "margin_bands": {
        "favorite_by_1": 0.2172,
        "favorite_by_2": 0.1239,
        "favorite_by_3plus": 0.0722,
        "draw": 0.2578,
        "underdog_by_1": 0.1872,
        "underdog_by_2plus": 0.136,
        "total_goals_4plus_in_matrix": 0.2759,
        "both_teams_2plus_in_matrix": 0.1462
      },
      "late_game_tail_note": "若一方60分钟后落后、早球、红牌/二黄、点球/定位球、门将失误或连续进攻换人出现，本场上沿比分尾部会被放大；赛前只作条件路径展示。",
      "tactical_tail_classification": "do_not_amplify",
      "tactical_triggers": [
        "Mexico transition_defense -0.30",
        "Ecuador transition_attack +0.35",
        "Mexico central_control 0.00",
        "Ecuador central_control +0.05"
      ],
      "markdown_path": "比赛/未开始比赛/32强/M79_2026-06-30_墨西哥_vs_厄瓜多尔_量化预测_v3.md",
      "markdown_status": "updated"
    },
    {
      "match_id": "M80",
      "match": "英格兰 vs 刚果金",
      "favorite": "英格兰",
      "expected_goals": {
        "team_a": 2.07,
        "team_b": 0.88,
        "total": 2.95,
        "xg_gap": 1.19
      },
      "probabilities_1x2": {
        "team_a_win": 0.649,
        "draw": 0.201,
        "team_b_win": 0.15,
        "sum": 1
      },
      "totals_probabilities": {
        "over_2_5": 0.5655,
        "under_2_5": 0.4345,
        "btts_yes": 0.5114,
        "btts_no": 0.4886
      },
      "knockout_big_score_tail_layer": {
        "trigger_status": "triggered",
        "tail_visibility_level": "high",
        "modeler_tail_visibility_level": "high",
        "tactical_tail_classification": "favorite_runaway_explicit",
        "red_team_verdict": "revise",
        "red_team_mainline_forbidden": false,
        "reason": "英格兰胜率 64.9%、xG 2.07-0.88、强度差 16，淘汰赛后段换人和追分空间会放大 3+ 球比分。",
        "recommended_display": "新增英格兰强队打穿尾部：3-0、3-1、4-0、4-1；刚果金若早丢球，弱队崩盘路径应显性展示。",
        "amplifiers_to_check": [
          "early_goal_before_30m",
          "red_card_or_second_yellow",
          "set_piece_goal_or_penalty",
          "goalkeeper_error_or_save_swing",
          "late_game_trailing_team_chase",
          "extra_time_not_in_90m_model"
        ],
        "red_team_guardrails": [
          "只作为 tail_visibility / risk layer 接入，不直接改 1X2、xG、大小球或 headline score。",
          "T-75 官方首发、最终伤停/分钟限制和同源赔率未闭合前，不能把大比分尾部写成可执行结论。",
          "红牌、早球、点球、门将失误和晚段追分只能作为条件尾部，不得作为稳定主预测。",
          "必须保留 raw Poisson 和 adjusted headline score，防止从过保守反向过度补偿。",
          "防止与 totals、BTTS、player_state、tactical_volatility 重复计权。"
        ],
        "no_probability_change": true,
        "no_headline_score_change": true,
        "no_betting_gate_change": true,
        "applied_at": "2026-06-29T00:35:00+08:00"
      },
      "big_score_tail_paths": {
        "strong_team_breakthrough_path": {
          "probability": 0.3106,
          "top_scores": [
            {
              "score": "3-0",
              "probability": 0.0774
            },
            {
              "score": "3-1",
              "probability": 0.0681
            },
            {
              "score": "4-0",
              "probability": 0.04
            },
            {
              "score": "4-1",
              "probability": 0.0352
            },
            {
              "score": "3-2",
              "probability": 0.03
            },
            {
              "score": "5-0",
              "probability": 0.0166
            }
          ]
        },
        "open_shootout_path": {
          "probability": 0.2638,
          "top_scores": [
            {
              "score": "3-1",
              "probability": 0.0681
            },
            {
              "score": "2-2",
              "probability": 0.0434
            },
            {
              "score": "4-1",
              "probability": 0.0352
            },
            {
              "score": "3-2",
              "probability": 0.03
            },
            {
              "score": "4-2",
              "probability": 0.0155
            },
            {
              "score": "5-1",
              "probability": 0.0146
            }
          ]
        },
        "weak_team_collapse_path": {
          "probability": 0.1902,
          "top_scores": [
            {
              "score": "3-0",
              "probability": 0.0774
            },
            {
              "score": "4-0",
              "probability": 0.04
            },
            {
              "score": "4-1",
              "probability": 0.0352
            },
            {
              "score": "5-0",
              "probability": 0.0166
            },
            {
              "score": "5-1",
              "probability": 0.0146
            },
            {
              "score": "5-2",
              "probability": 0.0064
            }
          ]
        },
        "late_game_chase_tail": {
          "probability": 0.2039,
          "top_scores": [
            {
              "score": "3-1",
              "probability": 0.0681
            },
            {
              "score": "2-2",
              "probability": 0.0434
            },
            {
              "score": "3-2",
              "probability": 0.03
            },
            {
              "score": "4-2",
              "probability": 0.0155
            },
            {
              "score": "2-3",
              "probability": 0.0127
            },
            {
              "score": "1-3",
              "probability": 0.0123
            }
          ]
        },
        "unallocated_above_5x5_tail": 0.0195
      },
      "margin_bands": {
        "favorite_by_1": 0.2419,
        "favorite_by_2": 0.1976,
        "favorite_by_3plus": 0.1902,
        "draw": 0.201,
        "underdog_by_1": 0.1029,
        "underdog_by_2plus": 0.0468,
        "total_goals_4plus_in_matrix": 0.3219,
        "both_teams_2plus_in_matrix": 0.1304
      },
      "late_game_tail_note": "若一方60分钟后落后、早球、红牌/二黄、点球/定位球、门将失误或连续进攻换人出现，本场上沿比分尾部会被放大；赛前只作条件路径展示。",
      "tactical_tail_classification": "favorite_runaway_explicit",
      "tactical_triggers": [
        "England central_control +0.45",
        "England set_piece +0.30",
        "DR Congo central_control -0.45",
        "DR Congo transition_defense -0.35"
      ],
      "markdown_path": "比赛/未开始比赛/32强/M80_2026-07-01_英格兰_vs_刚果金_量化预测_v3.md",
      "markdown_status": "updated"
    },
    {
      "match_id": "M81",
      "match": "美国 vs 波黑",
      "favorite": "美国",
      "expected_goals": {
        "team_a": 1.75,
        "team_b": 1,
        "total": 2.75,
        "xg_gap": 0.75
      },
      "probabilities_1x2": {
        "team_a_win": 0.5498,
        "draw": 0.2354,
        "team_b_win": 0.2148
      },
      "totals_probabilities": {
        "over_2_5": 0.5185,
        "under_2_5": 0.4815
      },
      "knockout_big_score_tail_layer": {
        "trigger_status": "observe",
        "tail_visibility_level": "medium",
        "modeler_tail_visibility_level": "medium",
        "tactical_tail_classification": "moderate_favorite_runaway",
        "red_team_verdict": "revise",
        "red_team_mainline_forbidden": true,
        "reason": "美国胜率 55.0%、xG 1.75-1.00 有优势，但 total xG 2.75 和强度差 7 更适合中等可见度。",
        "recommended_display": "新增观察级美国 3-1/3-0 尾部；不触发高可见度，因为波黑定位球和支点会压低纯碾压叙事。",
        "amplifiers_to_check": [
          "early_goal_before_30m",
          "red_card_or_second_yellow",
          "set_piece_goal_or_penalty",
          "goalkeeper_error_or_save_swing",
          "late_game_trailing_team_chase",
          "extra_time_not_in_90m_model"
        ],
        "red_team_guardrails": [
          "只作为 tail_visibility / risk layer 接入，不直接改 1X2、xG、大小球或 headline score。",
          "T-75 官方首发、最终伤停/分钟限制和同源赔率未闭合前，不能把大比分尾部写成可执行结论。",
          "红牌、早球、点球、门将失误和晚段追分只能作为条件尾部，不得作为稳定主预测。",
          "必须保留 raw Poisson 和 adjusted headline score，防止从过保守反向过度补偿。",
          "防止与 totals、BTTS、player_state、tactical_volatility 重复计权。"
        ],
        "no_probability_change": true,
        "no_headline_score_change": true,
        "no_betting_gate_change": true,
        "applied_at": "2026-06-29T00:35:00+08:00"
      },
      "big_score_tail_paths": {
        "strong_team_breakthrough_path": {
          "probability": 0.233055,
          "top_scores": [
            {
              "score": "3-0",
              "probability": 0.057102
            },
            {
              "score": "3-1",
              "probability": 0.057102
            },
            {
              "score": "3-2",
              "probability": 0.028551
            },
            {
              "score": "4-0",
              "probability": 0.024982
            },
            {
              "score": "4-1",
              "probability": 0.024982
            },
            {
              "score": "4-2",
              "probability": 0.012491
            }
          ]
        },
        "open_shootout_path": {
          "probability": 0.250315,
          "top_scores": [
            {
              "score": "3-1",
              "probability": 0.057102
            },
            {
              "score": "2-2",
              "probability": 0.048945
            },
            {
              "score": "3-2",
              "probability": 0.028551
            },
            {
              "score": "4-1",
              "probability": 0.024982
            },
            {
              "score": "1-3",
              "probability": 0.018646
            },
            {
              "score": "2-3",
              "probability": 0.016315
            }
          ]
        },
        "weak_team_collapse_path": {
          "probability": 0.128926,
          "top_scores": [
            {
              "score": "3-0",
              "probability": 0.057102
            },
            {
              "score": "4-0",
              "probability": 0.024982
            },
            {
              "score": "4-1",
              "probability": 0.024982
            },
            {
              "score": "5-0",
              "probability": 0.008744
            },
            {
              "score": "5-1",
              "probability": 0.008744
            },
            {
              "score": "5-2",
              "probability": 0.004372
            }
          ]
        },
        "late_game_chase_tail": {
          "probability": 0.205808,
          "top_scores": [
            {
              "score": "3-1",
              "probability": 0.057102
            },
            {
              "score": "2-2",
              "probability": 0.048945
            },
            {
              "score": "3-2",
              "probability": 0.028551
            },
            {
              "score": "1-3",
              "probability": 0.018646
            },
            {
              "score": "2-3",
              "probability": 0.016315
            },
            {
              "score": "4-2",
              "probability": 0.012491
            }
          ]
        },
        "unallocated_above_5x5_tail": 0.00972
      },
      "margin_bands": {
        "favorite_by_1": 0.242843,
        "favorite_by_2": 0.16894,
        "favorite_by_3plus": 0.128926,
        "draw": 0.2354,
        "underdog_by_1": 0.138767,
        "underdog_by_2plus": 0.075426,
        "total_goals_4plus_in_matrix": 0.287238,
        "both_teams_2plus_in_matrix": 0.135248
      },
      "late_game_tail_note": "若一方60分钟后落后、早球、红牌/二黄、点球/定位球、门将失误或连续进攻换人出现，本场上沿比分尾部会被放大；赛前只作条件路径展示。",
      "tactical_tail_classification": "moderate_favorite_runaway",
      "tactical_triggers": [
        "USA pressing +0.25",
        "USA wide_channel +0.35",
        "Bosnia transition_defense -0.35",
        "Bosnia defensive_line_risk -0.35"
      ],
      "markdown_path": "比赛/未开始比赛/32强/M81_2026-07-01_美国_vs_波黑_量化预测_v3.md",
      "markdown_status": "updated"
    },
    {
      "match_id": "M82",
      "match": "比利时 vs 塞内加尔",
      "favorite": "比利时",
      "expected_goals": {
        "team_a": 1.7,
        "team_b": 1.48,
        "total": 3.18,
        "xg_gap": 0.22
      },
      "probabilities_1x2": {
        "team_a_win": 0.4302,
        "draw": 0.2336,
        "team_b_win": 0.3361
      },
      "totals_probabilities": {
        "over_2_5": 0.6159,
        "under_2_5": 0.3841
      },
      "knockout_big_score_tail_layer": {
        "trigger_status": "triggered",
        "tail_visibility_level": "high",
        "modeler_tail_visibility_level": "high",
        "tactical_tail_classification": "open_two_way_tail_high",
        "red_team_verdict": "revise",
        "red_team_mainline_forbidden": true,
        "reason": "总 xG 3.18、Over2.5 61.6%、双方强度差 3，是 M73-M84 中最应显性展示大比分开放尾部的场次之一。",
        "recommended_display": "新增开放对攻和双向尾部：3-2、2-3、3-1、1-3、2-2、3-3；不只写比利时打穿，也要显示塞内加尔反打。",
        "amplifiers_to_check": [
          "early_goal_before_30m",
          "red_card_or_second_yellow",
          "set_piece_goal_or_penalty",
          "goalkeeper_error_or_save_swing",
          "late_game_trailing_team_chase",
          "extra_time_not_in_90m_model"
        ],
        "red_team_guardrails": [
          "只作为 tail_visibility / risk layer 接入，不直接改 1X2、xG、大小球或 headline score。",
          "T-75 官方首发、最终伤停/分钟限制和同源赔率未闭合前，不能把大比分尾部写成可执行结论。",
          "红牌、早球、点球、门将失误和晚段追分只能作为条件尾部，不得作为稳定主预测。",
          "必须保留 raw Poisson 和 adjusted headline score，防止从过保守反向过度补偿。",
          "防止与 totals、BTTS、player_state、tactical_volatility 重复计权。"
        ],
        "no_probability_change": true,
        "no_headline_score_change": true,
        "no_betting_gate_change": true,
        "applied_at": "2026-06-29T00:35:00+08:00"
      },
      "big_score_tail_paths": {
        "strong_team_breakthrough_path": {
          "probability": 0.202536,
          "top_scores": [
            {
              "score": "3-1",
              "probability": 0.050397
            },
            {
              "score": "3-2",
              "probability": 0.037293
            },
            {
              "score": "3-0",
              "probability": 0.034052
            },
            {
              "score": "4-1",
              "probability": 0.021419
            },
            {
              "score": "4-2",
              "probability": 0.01585
            },
            {
              "score": "4-0",
              "probability": 0.014472
            }
          ]
        },
        "open_shootout_path": {
          "probability": 0.350713,
          "top_scores": [
            {
              "score": "2-2",
              "probability": 0.065812
            },
            {
              "score": "3-1",
              "probability": 0.050397
            },
            {
              "score": "1-3",
              "probability": 0.038197
            },
            {
              "score": "3-2",
              "probability": 0.037293
            },
            {
              "score": "2-3",
              "probability": 0.032467
            },
            {
              "score": "4-1",
              "probability": 0.021419
            }
          ]
        },
        "weak_team_collapse_path": {
          "probability": 0.087534,
          "top_scores": [
            {
              "score": "3-0",
              "probability": 0.034052
            },
            {
              "score": "4-1",
              "probability": 0.021419
            },
            {
              "score": "4-0",
              "probability": 0.014472
            },
            {
              "score": "5-1",
              "probability": 0.007282
            },
            {
              "score": "5-2",
              "probability": 0.005389
            },
            {
              "score": "5-0",
              "probability": 0.00492
            }
          ]
        },
        "late_game_chase_tail": {
          "probability": 0.294751,
          "top_scores": [
            {
              "score": "2-2",
              "probability": 0.065812
            },
            {
              "score": "3-1",
              "probability": 0.050397
            },
            {
              "score": "1-3",
              "probability": 0.038197
            },
            {
              "score": "3-2",
              "probability": 0.037293
            },
            {
              "score": "2-3",
              "probability": 0.032467
            },
            {
              "score": "3-3",
              "probability": 0.018398
            }
          ]
        },
        "unallocated_above_5x5_tail": 0.012144
      },
      "margin_bands": {
        "favorite_by_1": 0.205727,
        "favorite_by_2": 0.128997,
        "favorite_by_3plus": 0.087534,
        "draw": 0.2336,
        "underdog_by_1": 0.179103,
        "underdog_by_2plus": 0.152885,
        "total_goals_4plus_in_matrix": 0.380879,
        "both_teams_2plus_in_matrix": 0.215102
      },
      "late_game_tail_note": "若一方60分钟后落后、早球、红牌/二黄、点球/定位球、门将失误或连续进攻换人出现，本场上沿比分尾部会被放大；赛前只作条件路径展示。",
      "tactical_tail_classification": "open_two_way_tail_high",
      "tactical_triggers": [
        "Belgium transition_attack +0.40",
        "Senegal transition_attack +0.35",
        "Belgium transition_defense -0.30",
        "Senegal game_state +0.25"
      ],
      "markdown_path": "比赛/未开始比赛/32强/M82_2026-07-01_比利时_vs_塞内加尔_量化预测_v3.md",
      "markdown_status": "updated"
    },
    {
      "match_id": "M83",
      "match": "葡萄牙 vs 克罗地亚",
      "favorite": "葡萄牙",
      "expected_goals": {
        "team_a": 1.58,
        "team_b": 1.08,
        "total": 2.66,
        "xg_gap": 0.5
      },
      "probabilities_1x2": {
        "team_a_win": 0.4893,
        "draw": 0.251,
        "team_b_win": 0.2597
      },
      "totals_probabilities": {
        "over_2_5": 0.4965,
        "under_2_5": 0.5035
      },
      "knockout_big_score_tail_layer": {
        "trigger_status": "observe",
        "tail_visibility_level": "low",
        "modeler_tail_visibility_level": "medium_low",
        "tactical_tail_classification": "selective_tail_only",
        "red_team_verdict": "revise",
        "red_team_mainline_forbidden": true,
        "reason": "葡萄牙有 xG 与实力优势，但 Over2.5 49.7%、克罗地亚控节奏能力较强，不应强行提高大比分可见度。",
        "recommended_display": "只新增葡萄牙 3-1/3-0 低可见度尾部；主叙事仍是控制型一球差。",
        "amplifiers_to_check": [
          "early_goal_before_30m",
          "red_card_or_second_yellow",
          "set_piece_goal_or_penalty",
          "goalkeeper_error_or_save_swing",
          "late_game_trailing_team_chase",
          "extra_time_not_in_90m_model"
        ],
        "red_team_guardrails": [
          "只作为 tail_visibility / risk layer 接入，不直接改 1X2、xG、大小球或 headline score。",
          "T-75 官方首发、最终伤停/分钟限制和同源赔率未闭合前，不能把大比分尾部写成可执行结论。",
          "红牌、早球、点球、门将失误和晚段追分只能作为条件尾部，不得作为稳定主预测。",
          "必须保留 raw Poisson 和 adjusted headline score，防止从过保守反向过度补偿。",
          "防止与 totals、BTTS、player_state、tactical_volatility 重复计权。"
        ],
        "no_probability_change": true,
        "no_headline_score_change": true,
        "no_betting_gate_change": true,
        "applied_at": "2026-06-29T00:35:00+08:00"
      },
      "big_score_tail_paths": {
        "strong_team_breakthrough_path": {
          "probability": 0.191463,
          "top_scores": [
            {
              "score": "3-1",
              "probability": 0.049662
            },
            {
              "score": "3-0",
              "probability": 0.045983
            },
            {
              "score": "3-2",
              "probability": 0.026817
            },
            {
              "score": "4-1",
              "probability": 0.019616
            },
            {
              "score": "4-0",
              "probability": 0.018163
            },
            {
              "score": "4-2",
              "probability": 0.010593
            }
          ]
        },
        "open_shootout_path": {
          "probability": 0.241813,
          "top_scores": [
            {
              "score": "2-2",
              "probability": 0.050919
            },
            {
              "score": "3-1",
              "probability": 0.049662
            },
            {
              "score": "3-2",
              "probability": 0.026817
            },
            {
              "score": "1-3",
              "probability": 0.023204
            },
            {
              "score": "4-1",
              "probability": 0.019616
            },
            {
              "score": "2-3",
              "probability": 0.018331
            }
          ]
        },
        "weak_team_collapse_path": {
          "probability": 0.099048,
          "top_scores": [
            {
              "score": "3-0",
              "probability": 0.045983
            },
            {
              "score": "4-1",
              "probability": 0.019616
            },
            {
              "score": "4-0",
              "probability": 0.018163
            },
            {
              "score": "5-1",
              "probability": 0.006199
            },
            {
              "score": "5-0",
              "probability": 0.00574
            },
            {
              "score": "5-2",
              "probability": 0.003347
            }
          ]
        },
        "late_game_chase_tail": {
          "probability": 0.203964,
          "top_scores": [
            {
              "score": "2-2",
              "probability": 0.050919
            },
            {
              "score": "3-1",
              "probability": 0.049662
            },
            {
              "score": "3-2",
              "probability": 0.026817
            },
            {
              "score": "1-3",
              "probability": 0.023204
            },
            {
              "score": "2-3",
              "probability": 0.018331
            },
            {
              "score": "4-2",
              "probability": 0.010593
            }
          ]
        },
        "unallocated_above_5x5_tail": 0.006573
      },
      "margin_bands": {
        "favorite_by_1": 0.235767,
        "favorite_by_2": 0.148769,
        "favorite_by_3plus": 0.099048,
        "draw": 0.251,
        "underdog_by_1": 0.161158,
        "underdog_by_2plus": 0.097704,
        "total_goals_4plus_in_matrix": 0.270537,
        "both_teams_2plus_in_matrix": 0.135514
      },
      "late_game_tail_note": "若一方60分钟后落后、早球、红牌/二黄、点球/定位球、门将失误或连续进攻换人出现，本场上沿比分尾部会被放大；赛前只作条件路径展示。",
      "tactical_tail_classification": "selective_tail_only",
      "tactical_triggers": [
        "Portugal wide_channel +0.30",
        "Croatia defensive_line_risk -0.30",
        "Croatia set_piece +0.25",
        "Portugal transition_defense -0.15"
      ],
      "markdown_path": "比赛/未开始比赛/32强/M83_2026-07-02_葡萄牙_vs_克罗地亚_量化预测_v3.md",
      "markdown_status": "updated"
    },
    {
      "match_id": "M84",
      "match": "西班牙 vs 奥地利",
      "favorite": "西班牙",
      "expected_goals": {
        "team_a": 1.92,
        "team_b": 1.05,
        "total": 2.97,
        "xg_gap": 0.87
      },
      "probabilities_1x2": {
        "team_a_win": 0.5765,
        "draw": 0.2201,
        "team_b_win": 0.2033
      },
      "totals_probabilities": {
        "over_2_5": 0.5701,
        "under_2_5": 0.4299
      },
      "knockout_big_score_tail_layer": {
        "trigger_status": "triggered",
        "tail_visibility_level": "high",
        "modeler_tail_visibility_level": "high",
        "tactical_tail_classification": "favorite_runaway_explicit",
        "red_team_verdict": "revise",
        "red_team_mainline_forbidden": false,
        "reason": "西班牙胜率 57.7%、xG 1.92-1.05、Over2.5 57.0%，奥地利高压既带来破门，也带来被打身后的崩盘风险。",
        "recommended_display": "新增西班牙打穿与奥地利高压互爆尾部：3-1、3-0、4-1、2-2、3-2；高压被穿透或早球会显著放大比分。",
        "amplifiers_to_check": [
          "early_goal_before_30m",
          "red_card_or_second_yellow",
          "set_piece_goal_or_penalty",
          "goalkeeper_error_or_save_swing",
          "late_game_trailing_team_chase",
          "extra_time_not_in_90m_model"
        ],
        "red_team_guardrails": [
          "只作为 tail_visibility / risk layer 接入，不直接改 1X2、xG、大小球或 headline score。",
          "T-75 官方首发、最终伤停/分钟限制和同源赔率未闭合前，不能把大比分尾部写成可执行结论。",
          "红牌、早球、点球、门将失误和晚段追分只能作为条件尾部，不得作为稳定主预测。",
          "必须保留 raw Poisson 和 adjusted headline score，防止从过保守反向过度补偿。",
          "防止与 totals、BTTS、player_state、tactical_volatility 重复计权。"
        ],
        "no_probability_change": true,
        "no_headline_score_change": true,
        "no_betting_gate_change": true,
        "applied_at": "2026-06-29T00:35:00+08:00"
      },
      "big_score_tail_paths": {
        "strong_team_breakthrough_path": {
          "probability": 0.270333,
          "top_scores": [
            {
              "score": "3-1",
              "probability": 0.063546
            },
            {
              "score": "3-0",
              "probability": 0.06052
            },
            {
              "score": "3-2",
              "probability": 0.033362
            },
            {
              "score": "4-1",
              "probability": 0.030502
            },
            {
              "score": "4-0",
              "probability": 0.02905
            },
            {
              "score": "4-2",
              "probability": 0.016014
            }
          ]
        },
        "open_shootout_path": {
          "probability": 0.288102,
          "top_scores": [
            {
              "score": "3-1",
              "probability": 0.063546
            },
            {
              "score": "2-2",
              "probability": 0.052127
            },
            {
              "score": "3-2",
              "probability": 0.033362
            },
            {
              "score": "4-1",
              "probability": 0.030502
            },
            {
              "score": "1-3",
              "probability": 0.019005
            },
            {
              "score": "2-3",
              "probability": 0.018245
            }
          ]
        },
        "weak_team_collapse_path": {
          "probability": 0.149089,
          "top_scores": [
            {
              "score": "3-0",
              "probability": 0.06052
            },
            {
              "score": "4-1",
              "probability": 0.030502
            },
            {
              "score": "4-0",
              "probability": 0.02905
            },
            {
              "score": "5-1",
              "probability": 0.011713
            },
            {
              "score": "5-0",
              "probability": 0.011155
            },
            {
              "score": "5-2",
              "probability": 0.006149
            }
          ]
        },
        "late_game_chase_tail": {
          "probability": 0.232695,
          "top_scores": [
            {
              "score": "3-1",
              "probability": 0.063546
            },
            {
              "score": "2-2",
              "probability": 0.052127
            },
            {
              "score": "3-2",
              "probability": 0.033362
            },
            {
              "score": "1-3",
              "probability": 0.019005
            },
            {
              "score": "2-3",
              "probability": 0.018245
            },
            {
              "score": "4-2",
              "probability": 0.016014
            }
          ]
        },
        "unallocated_above_5x5_tail": 0.014599
      },
      "margin_bands": {
        "favorite_by_1": 0.237324,
        "favorite_by_2": 0.176274,
        "favorite_by_3plus": 0.149089,
        "draw": 0.2201,
        "underdog_by_1": 0.129786,
        "underdog_by_2plus": 0.072804,
        "total_goals_4plus_in_matrix": 0.331451,
        "both_teams_2plus_in_matrix": 0.157299
      },
      "late_game_tail_note": "若一方60分钟后落后、早球、红牌/二黄、点球/定位球、门将失误或连续进攻换人出现，本场上沿比分尾部会被放大；赛前只作条件路径展示。",
      "tactical_tail_classification": "favorite_runaway_explicit",
      "tactical_triggers": [
        "Spain build_up_resistance +0.40",
        "Spain wide_channel +0.35",
        "Austria transition_defense -0.35",
        "Austria defensive_line_risk -0.35"
      ],
      "markdown_path": "比赛/未开始比赛/32强/M84_2026-07-02_西班牙_vs_奥地利_量化预测_v3.md",
      "markdown_status": "updated"
    }
  ]
}
